{
  "1. Thirty Days": [],
  "2. Three Months": [],
  "3. Six Months": [
    {
      "Difficulty": "MEDIUM",
      "Title": "Longest Substring Without Repeating Characters",
      "Frequency": 100.0,
      "Acceptance Rate": 0.3693618223350006,
      "Link": "https://leetcode.com/problems/longest-substring-without-repeating-characters",
      "Topics": "Hash Table, String, Sliding Window"
    }
  ],
  "4. More Than Six Months": [
    {
      "Difficulty": "MEDIUM",
      "Title": "Gas Station",
      "Frequency": 100.0,
      "Acceptance Rate": 0.463836988337989,
      "Link": "https://leetcode.com/problems/gas-station",
      "Topics": "Array, Greedy"
    },
    {
      "Difficulty": "MEDIUM",
      "Title": "LRU Cache",
      "Frequency": 100.0,
      "Acceptance Rate": 0.4521502513322059,
      "Link": "https://leetcode.com/problems/lru-cache",
      "Topics": "Hash Table, Linked List, Design, Doubly-Linked List"
    }
  ],
  "5. All": [
    {
      "Difficulty": "MEDIUM",
      "Title": "Gas Station",
      "Frequency": 100.0,
      "Acceptance Rate": 0.463836988337989,
      "Link": "https://leetcode.com/problems/gas-station",
      "Topics": "Array, Greedy"
    },
    {
      "Difficulty": "MEDIUM",
      "Title": "LRU Cache",
      "Frequency": 100.0,
      "Acceptance Rate": 0.4521502513322059,
      "Link": "https://leetcode.com/problems/lru-cache",
      "Topics": "Hash Table, Linked List, Design, Doubly-Linked List"
    },
    {
      "Difficulty": "MEDIUM",
      "Title": "Longest Substring Without Repeating Characters",
      "Frequency": 89.1,
      "Acceptance Rate": 0.3693618223350006,
      "Link": "https://leetcode.com/problems/longest-substring-without-repeating-characters",
      "Topics": "Hash Table, String, Sliding Window"
    }
  ]
}